CHANGELOG
LICENSE
MANIFEST.in
setup.py
django_objectset.egg-info/PKG-INFO
django_objectset.egg-info/SOURCES.txt
django_objectset.egg-info/dependency_links.txt
django_objectset.egg-info/requires.txt
django_objectset.egg-info/top_level.txt
objectset/__init__.py
objectset/decorators.py
objectset/exceptions.py
objectset/forms.py
objectset/models.py
objectset/resources.py