Metadata-Version: 1.0
Name: django-objectset
Version: 0.2.4
Summary: ObjectSet abstract class for set-like models
Home-page: http://cbmi.github.io/django-objectset/
Author: Byron Ruth
Author-email: b@devel.io
License: BSD
Keywords: object set
Platform: UNKNOWN
Classifier: Development Status :: 5 - Production/Stable
Classifier: License :: OSI Approved :: BSD License
Classifier: Programming Language :: Python :: 2.6
Classifier: Programming Language :: Python :: 2.7
Classifier: Framework :: Django
Classifier: Topic :: Internet :: WWW/HTTP
Classifier: Intended Audience :: Developers
Classifier: Intended Audience :: Science/Research
Classifier: Intended Audience :: Healthcare Industry
Classifier: Intended Audience :: Information Technology
